pyroll/cli/__init__.py
pyroll/cli/__main__.py
pyroll/cli/config.py
pyroll/cli/rich.py
pyroll/cli/program/__init__.py
pyroll/cli/program/create.py
pyroll/cli/program/edit.py
pyroll/cli/program/input.py
pyroll/cli/program/main.py
pyroll/cli/program/shell.py
pyroll/cli/program/solve.py
pyroll/cli/program/state.py
pyroll/cli/res/config.toml
pyroll/cli/res/input.py
pyroll_cli-3.0.0.dist-info/METADATA
pyroll_cli-3.0.0.dist-info/WHEEL
pyroll_cli-3.0.0.dist-info/entry_points.txt
pyroll_cli-3.0.0.dist-info/licenses/LICENSE
pyroll_cli-3.0.0.dist-info/RECORD
